webdriver_recorder/__init__.py
webdriver_recorder/browser.py
webdriver_recorder/export-report.py
webdriver_recorder/models.py
webdriver_recorder/plugin.py
webdriver_recorder/report_exporter.py
webdriver_recorder/templates/help.html
webdriver_recorder/templates/modal.html
webdriver_recorder/templates/modal_link.html
webdriver_recorder/templates/report.html
webdriver_recorder/templates/report_header.html
webdriver_recorder/templates/static/report.js
webdriver_recorder/templates/static/style.css
webdriver_recorder/templates/test_case.html
webdriver_recorder/templates/test_screenshots.html
webdriver_recorder/templates/toast-copied-to-clipboard.html
uw_webdriver_recorder-5.0.7.dist-info/entry_points.txt
uw_webdriver_recorder-5.0.7.dist-info/LICENSE
uw_webdriver_recorder-5.0.7.dist-info/LICENSE.chromedriver
uw_webdriver_recorder-5.0.7.dist-info/WHEEL
uw_webdriver_recorder-5.0.7.dist-info/METADATA
uw_webdriver_recorder-5.0.7.dist-info/RECORD
